setup.py
debatecrunch/__init__.py
debatecrunch.egg-info/PKG-INFO
debatecrunch.egg-info/SOURCES.txt
debatecrunch.egg-info/dependency_links.txt
debatecrunch.egg-info/not-zip-safe
debatecrunch.egg-info/top_level.txt