Metadata-Version: 1.0
Name: debatecrunch
Version: 0.1
Summary: Tools for analyzing debate transcripts
Home-page: UNKNOWN
Author: Dave Goodsmith
Author-email: UNKNOWN
License: MIT
Platform: UNKNOWN
